djoser/__init__.py
djoser/backends.py
djoser/compat.py
djoser/conf.py
djoser/constants.py
djoser/email.py
djoser/locale/de/LC_MESSAGES/django.po
djoser/locale/es/LC_MESSAGES/django.po
djoser/locale/fr/LC_MESSAGES/django.po
djoser/locale/id/LC_MESSAGES/django.po
djoser/locale/ja/LC_MESSAGES/django.po
djoser/locale/ka/LC_MESSAGES/django.po
djoser/locale/me/LC_MESSAGES/django.po
djoser/locale/pl/LC_MESSAGES/django.po
djoser/locale/pt_BR/LC_MESSAGES/django.po
djoser/locale/ru_RU/LC_MESSAGES/django.po
djoser/permissions.py
djoser/serializers.py
djoser/signals.py
djoser/social/__init__.py
djoser/social/backends/__init__.py
djoser/social/backends/facebook.py
djoser/social/serializers.py
djoser/social/token/__init__.py
djoser/social/token/jwt.py
djoser/social/urls.py
djoser/social/views.py
djoser/templates/email/activation.html
djoser/templates/email/confirmation.html
djoser/templates/email/password_changed_confirmation.html
djoser/templates/email/password_reset.html
djoser/templates/email/username_changed_confirmation.html
djoser/templates/email/username_reset.html
djoser/urls/__init__.py
djoser/urls/authtoken.py
djoser/urls/base.py
djoser/urls/jwt.py
djoser/utils.py
djoser/views.py
djoser/webauthn/__init__.py
djoser/webauthn/apps.py
djoser/webauthn/migrations/0001_initial.py
djoser/webauthn/migrations/__init__.py
djoser/webauthn/models.py
djoser/webauthn/serializers.py
djoser/webauthn/urls.py
djoser/webauthn/utils.py
djoser/webauthn/views.py
djoser_decacoaching-2.2.2.dist-info/LICENSE
djoser_decacoaching-2.2.2.dist-info/METADATA
djoser_decacoaching-2.2.2.dist-info/WHEEL
djoser_decacoaching-2.2.2.dist-info/RECORD
