Metadata-Version: 2.1
Name: djoser-decacoaching
Version: 2.2.2
Summary: REST implementation of Django authentication system.
Home-page: https://github.com/hisie/djoser
License: MIT
Author: Sunscrapers
Author-email: info@sunscrapers.com
Maintainer: Diego Cebrian
Maintainer-email: dcebrian@serincas.com
Requires-Python: >=3.8,<4.0
Classifier: Development Status :: 5 - Production/Stable
Classifier: Framework :: Django
Classifier: Framework :: Django :: 3.1
Classifier: Framework :: Django :: 3.2
Classifier: Framework :: Django :: 4.0
Classifier: Framework :: Django :: 4.1
Classifier: Framework :: Django :: 4.2
Classifier: Framework :: Django :: 5.0
Classifier: Intended Audience :: Developers
Classifier: License :: OSI Approved :: MIT License
Classifier: Operating System :: OS Independent
Classifier: Programming Language :: Python
Classifier: Programming Language :: Python :: 3
Classifier: Programming Language :: Python :: 3.8
Classifier: Programming Language :: Python :: 3.9
Classifier: Programming Language :: Python :: 3.10
Classifier: Programming Language :: Python :: 3.11
Classifier: Programming Language :: Python :: 3.12
Provides-Extra: djet
Provides-Extra: webauthn
Requires-Dist: django (>=3.0.0)
Requires-Dist: django-templated-mail (>=1.1.1,<2.0.0)
Requires-Dist: djangorestframework-simplejwt (>=5.0,<6.0)
Requires-Dist: djet (>=0.3.0,<0.4.0) ; extra == "djet"
Requires-Dist: social-auth-app-django (>=5.0.0,<6.0.0)
Requires-Dist: webauthn (<1.0) ; extra == "webauthn"
Project-URL: Documentation, https://djoser.readthedocs.io/
Project-URL: Repository, https://github.com/hisie/djoser
